app/main.py
app/routers/healthz.py
app/routers/hello_world.py
api_python_template-0.1.0.dist-info/METADATA
api_python_template-0.1.0.dist-info/WHEEL
api_python_template-0.1.0.dist-info/RECORD
